{"cameraMode":{"drawMode":0,"name":"Shaded","section":"Shading Mode"},"sceneLighting":false,"audioPlay":false,"sceneViewState":{"m_AlwaysRefresh":false,"showFog":true,"showSkybox":false,"showFlares":true,"showImageEffects":true,"showParticleSystems":true,"showVisualEffectGraphs":true,"m_FxEnabled":true},"in2DMode":false,"pivot":{"x":50.251129150390628,"y":-31.587682723999025,"z":-5.571604251861572},"rotation":{"x":-0.16805553436279298,"y":-0.7227180004119873,"z":0.1949194222688675,"w":-0.6441453099250794},"size":38.576114654541019,"orthographic":false}