{"cameraMode":{"drawMode":0,"name":"Shaded","section":"Shading Mode"},"sceneLighting":true,"audioPlay":false,"sceneViewState":{"m_AlwaysRefresh":false,"showFog":true,"showSkybox":true,"showFlares":true,"showImageEffects":true,"showParticleSystems":true,"showVisualEffectGraphs":true,"m_FxEnabled":true},"in2DMode":false,"pivot":{"x":-64.91776275634766,"y":2.136000394821167,"z":-35.41209411621094},"rotation":{"x":0.24430592358112336,"y":0.31035366654396059,"z":-0.08256052434444428,"w":0.9154895544052124},"size":8.498577117919922,"orthographic":true}